motor_orm/__init__.py
motor_orm/db.py
motor_orm/model.py
motor_orm/model_service.py
motor_orm/py.typed
motor_orm/utils.py
motor_orm-0.5.dist-info/WHEEL
motor_orm-0.5.dist-info/METADATA
motor_orm-0.5.dist-info/RECORD
