Metadata-Version: 2.1
Name: motor-orm
Version: 0.5
Summary: 
Author: Dmirty Simonov
Author-email: demalf@gmail.com
Requires-Python: >=3.7,<4.0
Classifier: Programming Language :: Python :: 3
Classifier: Programming Language :: Python :: 3.7
Classifier: Programming Language :: Python :: 3.8
Classifier: Programming Language :: Python :: 3.9
Requires-Dist: motor (>=2.3.0,<3.0.0)
Requires-Dist: pydantic (>=1.7.3,<2.0.0)
